{
  "columns": 3,
  "items": [
    {
      "name": "Este blog",
      "link": "https://github.com/lucianodlf/blog.lucianodlf",
      "image": "img/projects/hugo-blog.png",
      "visible": true
    },
    {
      "name": "gplnr (Extension Vscode)",
      "link": "https://github.com/lucianodlf/gplnr",
      "image": "img/projects/gplnr-icon.png",
      "visible": true
    },
    {
      "name": "Automatización Gastos (Experimento)",
      "link": "https://github.com/lucianodlf/ia-update-gestion-personal",
      "visible": true
    }
  ]
}
